{
  "name": "Ryan Low",
  "shortName": "Ryan",
  "nameToBold": "Ryan",
  "bio": [
    "Hello! I’m Ryan, an aspiring architect who is always on the lookout for new ideas to design inspiring and delightful spaces which encourage meaningful interaction among users, as well as incorporating environmentally sustainable design features and practices within our built environment.",
    "Outside of my architectural pursuits, you would find me playing musical instruments, travelling and exploring places, or simply spending time with friends, family, and my dog."
  ],
  "profilePath": "people/low-ryan/profile.JPG",
  "avatarPath": "people/low-ryan/character.png",
  "avatarBio": "Mr Rush",
  "icons": [
    {
      "url": "https://www.linkedin.com/in/designbyryanlow",
      "icon": "linkedin.png"
    },
    {
      "url": "https://issuu.com/lowryan/docs/portfolio_2021-2023",
      "icon": "portfolio.png"
    }
  ],
  "projects": [
    {
      "project": "",
      "studio": "",
      "imagePath": ""
    }
  ]
}